ALU_RISC-V.v
module ALU_RISCV(result,operand1,operand2,alu_opcode,flag);
input [31:0] operand1,operand2;
input [2:0] alu_opcode;
output [31:0] result;
input flag;
reg [31:0] res;
always @(*) begin
        res = 32'b0;
        case(alu_opcode)
                3'b000: res = operand1 + operand2; // ADD
                3'b001: res = operand1 - operand2; // SUB
                3'b010: res = operand1 & operand2; // AND
                3'b011: res = operand1 | operand2; // OR
                3'b100: res = operand1 ^ operand2; // XOR
                3'b101: res = flag ? ($signed(operand1) < $signed(operand2)) ? 32'b1 : 32'b0 : (operand1 < operand2) ? 32'b1 : 32'b0 ; // SLT
                3'b110: res = operand1 << operand2[4:0]; // SLL
                3'b111: res = operand1 >> operand2[4:0]; // SRL
                default : res = 32'b0;
        endcase
end
assign result = res;
endmodule

alu_control.v
module alu_control(alu_opcode,flag,funct3,funct7,opcode);
input [2:0] funct3;
input [6:0] funct7, opcode;
output reg [2:0] alu_opcode;
output flag;
always @ (*) begin
        case(opcode)
                7'b0110011 : begin
                        case(funct3)
                                3'b000 : alu_opcode = (funct7 == 7'b0100000) ? 3'b001 : 3'b000;
                                3'b001 : alu_opcode = 3'b110;
                                3'b010 : alu_opcode = 3'b101;
                                3'b011 : alu_opcode = 3'b101;
                                3'b100 : alu_opcode = 3'b100;
                                3'b101 : alu_opcode = 3'b111;
                                3'b110 : alu_opcode = 3'b011;
                                3'b111 : alu_opcode = 3'b010;
                                default : alu_opcode = 3'b0;
                        endcase
                end
                7'b0010011 : begin
                        case(funct3)
                                3'b000 : alu_opcode = 3'b000;
                                3'b001 : alu_opcode = 3'b110;
                                3'b010 : alu_opcode = 3'b101;
                                3'b011 : alu_opcode = 3'b101;
                                3'b100 : alu_opcode = 3'b100;
                                3'b101 : alu_opcode = 3'b111;
                                3'b110 : alu_opcode = 3'b011;
                                3'b111 : alu_opcode = 3'b010;
                                default : alu_opcode = 3'b0;
                        endcase
                end
                default : alu_opcode = 3'b000;
        endcase
end
assign flag = funct3==3'b010;
endmodule

alu_src_mux.v
module alu_src_mux(operand2,imm_out,read_data2,ALUsrc);
input ALUsrc;
input [31:0] imm_out ,read_data2;
output [31:0] operand2;
assign operand2 = ALUsrc ? imm_out : read_data2 ;
endmodule

register_file.v
module register_file(read_data1,read_data2,write_data,rd,rs1,rs2,RegWrite,rst,clk);
input clk,rst,RegWrite;
input [4:0] rd,rs1,rs2;
output [31:0] read_data1,read_data2;
input [31:0] write_data;
reg [31:0] Reg [0:31];
integer i;
always @ (posedge clk) begin
        if (rst) begin 
                for(i = 0; i < 32 ; i = i + 1) begin
                        Reg[i] <= 32'b0;
                end
        end else begin
                if (RegWrite) begin
                        Reg[rd] <= write_data;
                end else begin
                        Reg[rd] <= Reg[rd];
                end
        end
end
assign read_data1 = (rs1 == 5'b0) ? 32'b0 : Reg[rs1];
assign read_data2 = (rs2 == 5'b0) ? 32'b0 : Reg[rs2];
endmodule

control_unit.v
module control_unit(RegWrite,ALUSrc,opcode);
input [6:0] opcode;
output RegWrite,ALUSrc;
assign RegWrite = (opcode == 7'b0110011 || opcode == 7'b0010011) ? 1'b1 : 1'b0;
assign ALUSrc = (opcode == 7'b0010011) ? 1'b1 : 1'b0;
endmodule

imm_gen.v
module imm_gen(imm_out,instruction);
input [31:0] instruction;
output [31:0] imm_out;
assign imm_out = {{20{instruction[31]}},instruction[31:20]};
endmodule

instr_mem.v
module instr_mem(instruction,pc_addr);
input [31:0] pc_addr;
output [31:0] instruction;
reg [31:0] mem [0:63];
assign instruction = mem[pc_addr[31:2]];
endmodule

pc_reg.v
module pc_reg(pc_out,rst,clk);
input rst,clk;
output reg [31:0] pc_out;
always @ (posedge clk) begin
        if (rst) begin
                pc_out <= 32'b0;
        end else begin
                pc_out <= pc_out + 32'b00000000000000000000000000000100;
        end
end
endmodule

Riscv_core.v
module riscv_core(pc_out,rst,clk);
input rst,clk;
output [31:0] pc_out;
wire [4:0] rd,rs1,rs2;
wire RegWrite,ALUsrc,flag;
wire [6:0] opcode,funct7;
wire [2:0] alu_opcode,funct3;
wire [31:0] read_data1,read_data2,w1,imm_out,operand2,alu_result,instr;
pc_reg A1 (w1,rst,clk);
instr_mem A2 (instr,w1);
assign opcode = instr[6:0];
assign rd = instr[11:7];
assign funct3 = instr[14:12];
assign rs1 = instr[19:15];
assign rs2 = instr[24:20];
assign funct7 = instr[31:25];
assign pc_out = w1;
imm_gen A3 (imm_out,instr);
control_unit A4 (RegWrite,ALUsrc,opcode);
register_file A5 (read_data1,read_data2,alu_result,rd,rs1,rs2,RegWrite,rst,clk);
alu_src_mux A6 (operand2,imm_out,read_data2,ALUsrc);
alu_control A7 (alu_opcode,flag,funct3,funct7,opcode);
ALU_RISCV A8 (alu_result,read_data1,operand2,alu_opcode,flag);
endmodule

tb_riscv_core.v
`timescale 1ns / 1ps
module tb_riscv_core;
reg rst,clk;
wire [31:0] pc_out;
riscv_core uut (pc_out,rst,clk);
initial begin
        clk = 1'b0;
        rst = 1'b0;
end
always #5 clk = ~clk;
initial begin
$dumpfile("dump.vcd");
$dumpvars(0,tb_riscv_core);
$monitor("at time %t : clk = %b rst = %b pc_out=%b",$time,clk,rst,pc_out);
                rst = 1'b1; #10;
                uut.A2.mem[0] = 32'h00500093;
                uut.A2.mem[1] = 32'h00A00113;
                uut.A2.mem[2] = 32'h002081B3;
                uut.A2.mem[3] = 32'hFFD18213;
                uut.A2.mem[4] = 32'h004202B3;
                uut.A2.mem[5] = 32'hFFA00313;
                uut.A2.mem[6] = 32'h006283B3;
                uut.A2.mem[7] = 32'h40638433;
                rst = 1'b0;#10;
                #70;
                $display("---- Final Register Values ----");
                $display("x1 = %0d (expected 5)",  uut.A5.Reg[1]);
                $display("x2 = %0d (expected 10)", uut.A5.Reg[2]);
                $display("x3 = %0d (expected 15)", uut.A5.Reg[3]);
                $display("x4 = %0d (expected 12)", uut.A5.Reg[4]);
                $display("x5 = %0d (expected 24)", uut.A5.Reg[5]);
                $display("x6 = %0d (expected -6)", $signed(uut.A5.Reg[6]));
                $display("x7 = %0d (expected 18)", uut.A5.Reg[7]);
                $display("x8 = %0d (expected 24)", uut.A5.Reg[8]);
        $finish;
end
endmodule

dump.vcd
$date
	Fri Aug 07 00:53:35 2026
$end
$version
	Icarus Verilog
$end
$timescale
	1ps
$end
$scope module tb_riscv_core $end
$var wire 32 ! pc_out [31:0] $end
$var reg 1 " clk $end
$var reg 1 # rst $end
$scope module uut $end
$var wire 1 " clk $end
$var wire 32 $ pc_out [31:0] $end
$var wire 1 # rst $end
$var wire 32 % w1 [31:0] $end
$var wire 5 & rs2 [4:0] $end
$var wire 5 ' rs1 [4:0] $end
$var wire 32 ( read_data2 [31:0] $end
$var wire 32 ) read_data1 [31:0] $end
$var wire 5 * rd [4:0] $end
$var wire 32 + operand2 [31:0] $end
$var wire 7 , opcode [6:0] $end
$var wire 32 - instr [31:0] $end
$var wire 32 . imm_out [31:0] $end
$var wire 7 / funct7 [6:0] $end
$var wire 3 0 funct3 [2:0] $end
$var wire 1 1 flag $end
$var wire 32 2 alu_result [31:0] $end
$var wire 3 3 alu_opcode [2:0] $end
$var wire 1 4 RegWrite $end
$var wire 1 5 ALUsrc $end
$scope module A1 $end
$var wire 1 " clk $end
$var wire 1 # rst $end
$var reg 32 6 pc_out [31:0] $end
$upscope $end
$scope module A2 $end
$var wire 32 7 instruction [31:0] $end
$var wire 32 8 pc_addr [31:0] $end
$upscope $end
$scope module A3 $end
$var wire 32 9 instruction [31:0] $end
$var wire 32 : imm_out [31:0] $end
$upscope $end
$scope module A4 $end
$var wire 7 ; opcode [6:0] $end
$var wire 1 4 RegWrite $end
$var wire 1 5 ALUSrc $end
$upscope $end
$scope module A5 $end
$var wire 1 4 RegWrite $end
$var wire 1 " clk $end
$var wire 5 < rd [4:0] $end
$var wire 5 = rs1 [4:0] $end
$var wire 5 > rs2 [4:0] $end
$var wire 1 # rst $end
$var wire 32 ? write_data [31:0] $end
$var wire 32 @ read_data2 [31:0] $end
$var wire 32 A read_data1 [31:0] $end
$var integer 32 B i [31:0] $end
$upscope $end
$scope module A6 $end
$var wire 1 5 ALUsrc $end
$var wire 32 C imm_out [31:0] $end
$var wire 32 D read_data2 [31:0] $end
$var wire 32 E operand2 [31:0] $end
$upscope $end
$scope module A7 $end
$var wire 3 F funct3 [2:0] $end
$var wire 7 G funct7 [6:0] $end
$var wire 7 H opcode [6:0] $end
$var wire 1 1 flag $end
$var reg 3 I alu_opcode [2:0] $end
$upscope $end
$scope module A8 $end
$var wire 3 J alu_opcode [2:0] $end
$var wire 1 1 flag $end
$var wire 32 K operand1 [31:0] $end
$var wire 32 L operand2 [31:0] $end
$var wire 32 M result [31:0] $end
$var reg 32 N res [31:0] $end
$upscope $end
$upscope $end
$upscope $end
$enddefinitions $end
$comment Show the parameter values. $end
$dumpall
$end
#0
$dumpvars
bx N
bx M
bx L
bx K
bx J
bx I
bx H
bx G
bx F
bx E
bx D
bx C
bx B
bx A
bx @
bx ?
bx >
bx =
bx <
bx ;
bx :
bx 9
bx 8
bx 7
bx 6
x5
x4
bx 3
bx 2
x1
bx 0
bx /
bx .
bx -
bx ,
bx +
bx *
bx )
bx (
bx '
bx &
bx %
bx $
1#
0"
bx !
$end
#5000
b0 !
b0 $
b0 %
b0 6
b0 8
b100000 B
1"
#10000
14
b101 +
b101 E
b101 L
b0 (
b0 @
b0 D
b0 )
b0 A
b0 K
b101 2
b101 ?
b101 M
b101 N
15
b0 3
b0 I
b0 J
b101 .
b101 :
b101 C
b0 /
b0 G
b101 &
b101 >
b0 '
b0 =
01
b0 0
b0 F
b1 *
b1 <
b10011 ,
b10011 ;
b10011 H
0"
0#
b10100000000000010010011 -
b10100000000000010010011 7
b10100000000000010010011 9
#15000
b1010 2
b1010 ?
b1010 M
b1010 N
b1010 +
b1010 E
b1010 L
b1010 .
b1010 :
b1010 C
b1010 &
b1010 >
b10 *
b10 <
b101000000000000100010011 -
b101000000000000100010011 7
b101000000000000100010011 9
b100 !
b100 $
b100 %
b100 6
b100 8
1"
#20000
0"
#25000
b1111 2
b1111 ?
b1111 M
b1111 N
b1010 (
b1010 @
b1010 D
b101 )
b101 A
b101 K
05
b10 .
b10 :
b10 C
b10 &
b10 >
b1 '
b1 =
b11 *
b11 <
b110011 ,
b110011 ;
b110011 H
b1000001000000110110011 -
b1000001000000110110011 7
b1000001000000110110011 9
b1000 !
b1000 $
b1000 %
b1000 6
b1000 8
1"
#30000
0"
#35000
b1100 2
b1100 ?
b1100 M
b1100 N
b11111111111111111111111111111101 +
b11111111111111111111111111111101 E
b11111111111111111111111111111101 L
b0 (
b0 @
b0 D
b1111 )
b1111 A
b1111 K
15
b11111111111111111111111111111101 .
b11111111111111111111111111111101 :
b11111111111111111111111111111101 C
b1111111 /
b1111111 G
b11101 &
b11101 >
b11 '
b11 =
b100 *
b100 <
b10011 ,
b10011 ;
b10011 H
b11111111110100011000001000010011 -
b11111111110100011000001000010011 7
b11111111110100011000001000010011 9
b1100 !
b1100 $
b1100 %
b1100 6
b1100 8
1"
#40000
0"
#45000
b11000 2
b11000 ?
b11000 M
b11000 N
b1100 +
b1100 E
b1100 L
b1100 (
b1100 @
b1100 D
b1100 )
b1100 A
b1100 K
05
b100 .
b100 :
b100 C
b0 /
b0 G
b100 &
b100 >
b100 '
b100 =
b101 *
b101 <
b110011 ,
b110011 ;
b110011 H
b10000100000001010110011 -
b10000100000001010110011 7
b10000100000001010110011 9
b10000 !
b10000 $
b10000 %
b10000 6
b10000 8
1"
#50000
0"
#55000
b11111111111111111111111111111010 2
b11111111111111111111111111111010 ?
b11111111111111111111111111111010 M
b11111111111111111111111111111010 N
b11111111111111111111111111111010 +
b11111111111111111111111111111010 E
b11111111111111111111111111111010 L
b0 (
b0 @
b0 D
b0 )
b0 A
b0 K
15
b11111111111111111111111111111010 .
b11111111111111111111111111111010 :
b11111111111111111111111111111010 C
b1111111 /
b1111111 G
b11010 &
b11010 >
b0 '
b0 =
b110 *
b110 <
b10011 ,
b10011 ;
b10011 H
b11111111101000000000001100010011 -
b11111111101000000000001100010011 7
b11111111101000000000001100010011 9
b10100 !
b10100 $
b10100 %
b10100 6
b10100 8
1"
#60000
0"
#65000
b10010 2
b10010 ?
b10010 M
b10010 N
b11111111111111111111111111111010 (
b11111111111111111111111111111010 @
b11111111111111111111111111111010 D
b11000 )
b11000 A
b11000 K
05
b110 .
b110 :
b110 C
b0 /
b0 G
b110 &
b110 >
b101 '
b101 =
b111 *
b111 <
b110011 ,
b110011 ;
b110011 H
b11000101000001110110011 -
b11000101000001110110011 7
b11000101000001110110011 9
b11000 !
b11000 $
b11000 %
b11000 6
b11000 8
1"
#70000
0"
#75000
b11000 2
b11000 ?
b11000 M
b11000 N
b1 3
b1 I
b1 J
b10010 )
b10010 A
b10010 K
b10000000110 .
b10000000110 :
b10000000110 C
b100000 /
b100000 G
b111 '
b111 =
b1000 *
b1000 <
b1000000011000111000010000110011 -
b1000000011000111000010000110011 7
b1000000011000111000010000110011 9
b11100 !
b11100 $
b11100 %
b11100 6
b11100 8
1"
#80000
0"
#85000
b11000 +
b11000 E
b11000 L
b10000 2
b10000 ?
b10000 M
b10000 N
b11000 (
b11000 @
b11000 D
b10 3
b10 I
b10 J
b1000 .
b1000 :
b1000 C
b0 /
b0 G
b1000 &
b1000 >
b111 0
b111 F
b1001 *
b1001 <
b100000111111010010110011 -
b100000111111010010110011 7
b100000111111010010110011 9
b100000 !
b100000 $
b100000 %
b100000 6
b100000 8
1"
#90000
0"
#95000
b11010 2
b11010 ?
b11010 M
b11010 N
b11 3
b11 I
b11 J
b110 0
b110 F
b1010 *
b1010 <
b100000111110010100110011 -
b100000111110010100110011 7
b100000111110010100110011 9
b100100 !
b100100 $
b100100 %
b100100 6
b100100 8
1"
#100000
0"
#105000
b1010 2
b1010 ?
b1010 M
b1010 N
b100 3
b100 I
b100 J
b100 0
b100 F
b1011 *
b1011 <
b100000111100010110110011 -
b100000111100010110110011 7
b100000111100010110110011 9
b101000 !
b101000 $
b101000 %
b101000 6
b101000 8
1"
#110000
0"
#115000
b1 2
b1 ?
b1 M
b1 N
b101 3
b101 I
b101 J
b11 0
b11 F
b1100 *
b1100 <
b100000111011011000110011 -
b100000111011011000110011 7
b100000111011011000110011 9
b101100 !
b101100 $
b101100 %
b101100 6
b101100 8
1"
#120000
0"
#125000
b11111111111111111111111111111010 +
b11111111111111111111111111111010 E
b11111111111111111111111111111010 L
b11111111111111111111111111111010 (
b11111111111111111111111111111010 @
b11111111111111111111111111111010 D
b0 2
b0 ?
b0 M
b0 N
b110 .
b110 :
b110 C
b110 &
b110 >
11
b10 0
b10 F
b1101 *
b1101 <
b11000111010011010110011 -
b11000111010011010110011 7
b11000111010011010110011 9
b110000 !
b110000 $
b110000 %
b110000 6
b110000 8
1"
#130000
0"
#135000
b10010 +
b10010 E
b10010 L
b10010 (
b10010 @
b10010 D
b1 )
b1 A
b1 K
b110 3
b110 I
b110 J
b1000000000000000000 2
b1000000000000000000 ?
b1000000000000000000 M
b1000000000000000000 N
b111 .
b111 :
b111 C
b111 &
b111 >
b1100 '
b1100 =
01
b1 0
b1 F
b1110 *
b1110 <
b11101100001011100110011 -
b11101100001011100110011 7
b11101100001011100110011 9
b110100 !
b110100 $
b110100 %
b110100 6
b110100 8
1"
#140000
0"
#145000
b1 2
b1 ?
b1 M
b1 N
b1000000000000000000 )
b1000000000000000000 A
b1000000000000000000 K
b111 3
b111 I
b111 J
b1110 '
b1110 =
b101 0
b101 F
b1111 *
b1111 <
b11101110101011110110011 -
b11101110101011110110011 7
b11101110101011110110011 9
b111000 !
b111000 $
b111000 %
b111000 6
b111000 8
1"
#150000
0"
#155000
b10000 +
b10000 E
b10000 L
b10000 2
b10000 ?
b10000 M
b10000 N
b0 (
b0 @
b0 D
b10010 )
b10010 A
b10010 K
15
b10 3
b10 I
b10 J
b10000 .
b10000 :
b10000 C
b10000 &
b10000 >
b111 '
b111 =
b111 0
b111 F
b10000 *
b10000 <
b10011 ,
b10011 ;
b10011 H
b1000000111111100000010011 -
b1000000111111100000010011 7
b1000000111111100000010011 9
b111100 !
b111100 $
b111100 %
b111100 6
b111100 8
1"
#160000
0"
#165000
b10010 2
b10010 ?
b10010 M
b10010 N
b11 3
b11 I
b11 J
b110 0
b110 F
b10001 *
b10001 <
b1000000111110100010010011 -
b1000000111110100010010011 7
b1000000111110100010010011 9
b10000 (
b10000 @
b10000 D
b1000000 !
b1000000 $
b1000000 %
b1000000 6
b1000000 8
1"
#170000
0"
#175000
b10 2
b10 ?
b10 M
b10 N
b100 3
b100 I
b100 J
b100 0
b100 F
b10010 *
b10010 <
b1000000111100100100010011 -
b1000000111100100100010011 7
b1000000111100100100010011 9
b1000100 !
b1000100 $
b1000100 %
b1000100 6
b1000100 8
1"
#180000
0"
#185000
b1001000 2
b1001000 ?
b1001000 M
b1001000 N
b10 +
b10 E
b10 L
b1010 (
b1010 @
b1010 D
b110 3
b110 I
b110 J
b10 .
b10 :
b10 C
b10 &
b10 >
b1 0
b1 F
b10011 *
b10011 <
b1000111001100110010011 -
b1000111001100110010011 7
b1000111001100110010011 9
b1001000 !
b1001000 $
b1001000 %
b1001000 6
b1001000 8
1"
#190000
0"
#195000
b10010 2
b10010 ?
b10010 M
b10010 N
b1001000 )
b1001000 A
b1001000 K
b111 3
b111 I
b111 J
b10011 '
b10011 =
b101 0
b101 F
b10100 *
b10100 <
b1010011101101000010011 -
b1010011101101000010011 7
b1010011101101000010011 9
b1001100 !
b1001100 $
b1001100 %
b1001100 6
b1001100 8
1"
#200000
0"
#205000
b0 2
b0 ?
b0 M
b0 N
b10010 )
b10010 A
b10010 K
b101 3
b101 I
b101 J
b111 '
b111 =
b11 0
b11 F
b10101 *
b10101 <
b1000111011101010010011 -
b1000111011101010010011 7
b1000111011101010010011 9
b1010000 !
b1010000 $
b1010000 %
b1010000 6
b1010000 8
1"
#210000
0"
#215000
b1 2
b1 ?
b1 M
b1 N
b11111111111111111111111111111110 +
b11111111111111111111111111111110 E
b11111111111111111111111111111110 L
b0 (
b0 @
b0 D
b11111111111111111111111111111010 )
b11111111111111111111111111111010 A
b11111111111111111111111111111010 K
b11111111111111111111111111111110 .
b11111111111111111111111111111110 :
b11111111111111111111111111111110 C
b1111111 /
b1111111 G
b11110 &
b11110 >
b110 '
b110 =
11
b10 0
b10 F
b10110 *
b10110 <
b11111111111000110010101100010011 -
b11111111111000110010101100010011 7
b11111111111000110010101100010011 9
b1010100 !
b1010100 $
b1010100 %
b1010100 6
b1010100 8
1"
#220000
0"
#225000
x4
bx +
bx E
bx L
bx (
bx @
bx D
bx )
bx A
bx K
bx 2
bx ?
bx M
bx N
x5
b0 3
b0 I
b0 J
bx .
bx :
bx C
bx /
bx G
bx &
bx >
bx '
bx =
x1
bx 0
bx F
bx *
bx <
bx ,
bx ;
bx H
bx -
bx 7
bx 9
b1011000 !
b1011000 $
b1011000 %
b1011000 6
b1011000 8
1"
#230000
0"
#235000
b1011100 !
b1011100 $
b1011100 %
b1011100 6
b1011100 8
1"
#240000
0"
#245000
b1100000 !
b1100000 $
b1100000 %
b1100000 6
b1100000 8
1"
#250000
0"
#255000
b1100100 !
b1100100 $
b1100100 %
b1100100 6
b1100100 8
1"
#260000
0"
#265000
b1101000 !
b1101000 $
b1101000 %
b1101000 6
b1101000 8
1"
#270000
0"
#275000
b1101100 !
b1101100 $
b1101100 %
b1101100 6
b1101100 8
1"
#280000
0"
#285000
b1110000 !
b1110000 $
b1110000 %
b1110000 6
b1110000 8
1"
#290000
0"
#295000
b1110100 !
b1110100 $
b1110100 %
b1110100 6
b1110100 8
1"
#300000
0"
#305000
b1111000 !
b1111000 $
b1111000 %
b1111000 6
b1111000 8
1"
#310000
0"
#315000
b1111100 !
b1111100 $
b1111100 %
b1111100 6
b1111100 8
1"
#320000
0"
#325000
b10000000 !
b10000000 $
b10000000 %
b10000000 6
b10000000 8
1"
#330000
0"
#335000
b10000100 !
b10000100 $
b10000100 %
b10000100 6
b10000100 8
1"
#340000
0"
#345000
b10001000 !
b10001000 $
b10001000 %
b10001000 6
b10001000 8
1"
#350000
0"
#355000
b10001100 !
b10001100 $
b10001100 %
b10001100 6
b10001100 8
1"
#360000
0"
#365000
b10010000 !
b10010000 $
b10010000 %
b10010000 6
b10010000 8
1"
#370000
0"
#375000
b10010100 !
b10010100 $
b10010100 %
b10010100 6
b10010100 8
1"
#380000
0"
#385000
b10011000 !
b10011000 $
b10011000 %
b10011000 6
b10011000 8
1"
#390000
0"
#395000
b10011100 !
b10011100 $
b10011100 %
b10011100 6
b10011100 8
1"
#400000
0"
#405000
b10100000 !
b10100000 $
b10100000 %
b10100000 6
b10100000 8
1"
#410000
0"
#415000
b10100100 !
b10100100 $
b10100100 %
b10100100 6
b10100100 8
1"
#420000
0"
#425000
b10101000 !
b10101000 $
b10101000 %
b10101000 6
b10101000 8
1"
#430000
0"
#435000
b10101100 !
b10101100 $
b10101100 %
b10101100 6
b10101100 8
1"
#440000
0"
#445000
b10110000 !
b10110000 $
b10110000 %
b10110000 6
b10110000 8
1"
#450000
0"
#455000
b10110100 !
b10110100 $
b10110100 %
b10110100 6
b10110100 8
1"
#460000
0"
#465000
b10111000 !
b10111000 $
b10111000 %
b10111000 6
b10111000 8
1"
#470000
0"
#475000
b10111100 !
b10111100 $
b10111100 %
b10111100 6
b10111100 8
1"
#480000
0"
#485000
b11000000 !
b11000000 $
b11000000 %
b11000000 6
b11000000 8
1"
#490000
0"
#495000
b11000100 !
b11000100 $
b11000100 %
b11000100 6
b11000100 8
1"
#500000
0"
#505000
14
b10000 +
b10000 E
b10000 L
b10000 (
b10000 @
b10000 D
b10010 )
b10010 A
b10010 K
b10000 2
b10000 ?
b10000 M
b10000 N
15
b10 3
b10 I
b10 J
b10000 .
b10000 :
b10000 C
b0 /
b0 G
b10000 &
b10000 >
b111 '
b111 =
01
b111 0
b111 F
b10000 *
b10000 <
b10011 ,
b10011 ;
b10011 H
b1000000111111100000010011 -
b1000000111111100000010011 7
b1000000111111100000010011 9
b11001000 !
b11001000 $
b11001000 %
b11001000 6
b11001000 8
1"
#510000
0"
#515000
x4
bx +
bx E
bx L
bx (
bx @
bx D
bx )
bx A
bx K
bx 2
bx ?
bx M
bx N
x5
b0 3
b0 I
b0 J
bx .
bx :
bx C
bx /
bx G
bx &
bx >
bx '
bx =
x1
bx 0
bx F
bx *
bx <
bx ,
bx ;
bx H
bx -
bx 7
bx 9
b11001100 !
b11001100 $
b11001100 %
b11001100 6
b11001100 8
1"
#520000
0"
#525000
b11010000 !
b11010000 $
b11010000 %
b11010000 6
b11010000 8
1"
#530000
0"
#535000
b11010100 !
b11010100 $
b11010100 %
b11010100 6
b11010100 8
1"
#540000
0"
#545000
b11011000 !
b11011000 $
b11011000 %
b11011000 6
b11011000 8
1"
#550000
0"
#555000
b11011100 !
b11011100 $
b11011100 %
b11011100 6
b11011100 8
1"
#560000
0"
#565000
b11100000 !
b11100000 $
b11100000 %
b11100000 6
b11100000 8
1"
#570000
0"
#575000
b11100100 !
b11100100 $
b11100100 %
b11100100 6
b11100100 8
1"
#580000
0"
#585000
b11101000 !
b11101000 $
b11101000 %
b11101000 6
b11101000 8
1"
#590000
0"
#595000
b11101100 !
b11101100 $
b11101100 %
b11101100 6
b11101100 8
1"
#600000
0"
#605000
b11110000 !
b11110000 $
b11110000 %
b11110000 6
b11110000 8
1"
#610000
0"
#615000
b11110100 !
b11110100 $
b11110100 %
b11110100 6
b11110100 8
1"
#620000
0"
#625000
b11111000 !
b11111000 $
b11111000 %
b11111000 6
b11111000 8
1"
#630000
0"
#635000
14
b10010 +
b10010 E
b10010 L
b10 (
b10 @
b10 D
b10010 )
b10010 A
b10010 K
b10010 2
b10010 ?
b10010 M
b10010 N
15
b10 3
b10 I
b10 J
b10010 .
b10010 :
b10010 C
b0 /
b0 G
b10010 &
b10010 >
b111 '
b111 =
01
b111 0
b111 F
b10000 *
b10000 <
b10011 ,
b10011 ;
b10011 H
b1001000111111100000010011 -
b1001000111111100000010011 7
b1001000111111100000010011 9
b11111100 !
b11111100 $
b11111100 %
b11111100 6
b11111100 8
1"
#640000
0"
#645000
x4
bx +
bx E
bx L
bx (
bx @
bx D
bx )
bx A
bx K
bx 2
bx ?
bx M
bx N
x5
b0 3
b0 I
b0 J
bx .
bx :
bx C
bx /
bx G
bx &
bx >
bx '
bx =
x1
bx 0
bx F
bx *
bx <
bx ,
bx ;
bx H
bx -
bx 7
bx 9
b100000000 !
b100000000 $
b100000000 %
b100000000 6
b100000000 8
1"
