ALU_RISC-V.v
module ALU_RISCV(result,operand1,operand2,alu_opcode,flag);
input [31:0] operand1,operand2;
input [2:0] alu_opcode;
output [31:0] result;
input flag;
reg [31:0] res;
always @(*) begin
        res = 32'b0;
        case(alu_opcode)
                3'b000: res = operand1 + operand2; // ADD
                3'b001: res = operand1 - operand2; // SUB
                3'b010: res = operand1 & operand2; // AND
                3'b011: res = operand1 | operand2; // OR
                3'b100: res = operand1 ^ operand2; // XOR
                3'b101: res = flag ? ($signed(operand1) < $signed(operand2)) ? 32'b1 : 32'b0 : (operand1 < operand2) ? 32'b1 : 32'b0 ; // SLT
                3'b110: res = operand1 << operand2[4:0]; // SLL
                3'b111: res = operand1 >> operand2[4:0]; // SRL
                default : res = 32'b0;
        endcase
end
assign result = res;
endmodule

alu_control.v
module alu_control(alu_opcode,flag,funct3,funct7,opcode);
input [2:0] funct3;
input [6:0] funct7, opcode;
output reg [2:0] alu_opcode;
output flag;
always @ (*) begin
        case(opcode)
                7'b0110011 : begin
                        case(funct3)
                                3'b000 : alu_opcode = (funct7 == 7'b0100000) ? 3'b001 : 3'b000;
                                3'b001 : alu_opcode = 3'b110;
                                3'b010 : alu_opcode = 3'b101;
                                3'b011 : alu_opcode = 3'b101;
                                3'b100 : alu_opcode = 3'b100;
                                3'b101 : alu_opcode = 3'b111;
                                3'b110 : alu_opcode = 3'b011;
                                3'b111 : alu_opcode = 3'b010;
                                default : alu_opcode = 3'b0;
                        endcase
                end
                7'b0010011 : begin
                        case(funct3)
                                3'b000 : alu_opcode = 3'b000;
                                3'b001 : alu_opcode = 3'b110;
                                3'b010 : alu_opcode = 3'b101;
                                3'b011 : alu_opcode = 3'b101;
                                3'b100 : alu_opcode = 3'b100;
                                3'b101 : alu_opcode = 3'b111;
                                3'b110 : alu_opcode = 3'b011;
                                3'b111 : alu_opcode = 3'b010;
                                default : alu_opcode = 3'b0;
                        endcase
                end
                default : alu_opcode = 3'b000;
        endcase
end
assign flag = funct3==3'b010;
endmodule

alu_src_mux.v
module alu_src_mux(operand2,imm_out,read_data2,ALUsrc);
input ALUsrc;
input [31:0] imm_out ,read_data2;
output [31:0] operand2;
assign operand2 = ALUsrc ? imm_out : read_data2 ;
endmodule

register_file.v
module register_file(Reg_output,read_data1,read_data2,write_data,rd,rs1,rs2,RegWrite,rst,clk);
input clk,rst,RegWrite;
input [4:0] rd,rs1,rs2;
output [31:0] read_data1,read_data2;
output reg [31:0] Reg_output;
input [31:0] write_data;
reg [31:0] Reg [0:31];
integer i;
always @ (posedge clk) begin
        if (rst) begin 
                for(i = 0; i < 32 ; i = i + 1) begin
                        Reg[i] <= 32'b0;
                end
                Reg_output <= 32'b0;
        end else begin
                if (RegWrite && rd != 5'b0) begin
                        Reg[rd] <= write_data;
                        Reg_output <= write_data;
                end else begin
                        Reg[rd] <= Reg[rd];
                        Reg_output <= Reg[rd];
                end
        end
end
assign read_data1 = (rs1 == 5'b0) ? 32'b0 : Reg[rs1];
assign read_data2 = (rs2 == 5'b0) ? 32'b0 : Reg[rs2];
endmodule

control_unit.v
module control_unit(RegWrite,ALUSrc,opcode);
input [6:0] opcode;
output RegWrite,ALUSrc;
assign RegWrite = (opcode == 7'b0110011 || opcode == 7'b0010011) ? 1'b1 : 1'b0;
assign ALUSrc = (opcode == 7'b0010011) ? 1'b1 : 1'b0;
endmodule

imm_gen.v
module imm_gen(imm_out,instruction);
input [31:0] instruction;
output [31:0] imm_out;
assign imm_out = {{20{instruction[31]}},instruction[31:20]};
endmodule

instr_mem.v
module instr_mem(instruction,address,number,pc_addr);
input [31:0] pc_addr,address,number;
output [31:0] instruction;
reg [31:0] mem [0:63];
always @(*) begin
        mem[address[31:0]] = number;
end
assign instruction = mem[pc_addr[31:2]];
endmodule

address_sel.v
module address_sel(fetch_address,jump,address,pc_out);
input jump;
input [31:0] address,pc_out;
output [31:0] fetch_address;
assign fetch_address = jump ? address<<2'd2 : pc_out;
endmodule

pc_reg.v
module pc_reg(pc_out,jump,rst,clk);
input rst,clk,jump;
output reg [31:0] pc_out;
always @ (posedge clk) begin
        if (rst) begin
                pc_out <= 32'b0;
        end else begin
                if(jump) begin
                        pc_out<=pc_out;
                end else begin
                        pc_out <= pc_out + 32'd4;
                end     
        end
end
endmodule

Riscv_core.v
module riscv_core(Reg_output,address,number,jump,rst,clk);
input rst,clk,jump;
input [31:0] address,number;
output [31:0] Reg_output;
wire [4:0] rd,rs1,rs2;
wire RegWrite,ALUsrc,flag;
wire [6:0] opcode,funct7;
wire [2:0] alu_opcode,funct3;
wire [31:0] read_data1,read_data2,imm_out,operand2,alu_result,instr,pc_out,fetch_address;
pc_reg A1 (pc_out,jump,rst,clk);
address_sel A2 (fetch_address,jump,address,pc_out);
instr_mem A3 (instr,address,number,fetch_address);
assign opcode = instr[6:0];
assign rd = instr[11:7];
assign funct3 = instr[14:12];
assign rs1 = instr[19:15];
assign rs2 = instr[24:20];
assign funct7 = instr[31:25];
imm_gen A4 (imm_out,instr);
control_unit A5 (RegWrite,ALUsrc,opcode);
register_file A6 (Reg_output,read_data1,read_data2,alu_result,rd,rs1,rs2,RegWrite,rst,clk);
alu_src_mux A7 (operand2,imm_out,read_data2,ALUsrc);
alu_control A8 (alu_opcode,flag,funct3,funct7,opcode);
ALU_RISCV A9 (alu_result,read_data1,operand2,alu_opcode,flag);
endmodule

tb_riscv_core.v
`timescale 1ns / 1ps
module tb_riscv_core;
reg rst,clk,jump;
reg [31:0] address,number;
wire [31:0] Reg_output;
integer errors = 0;
integer test_num = 0;
riscv_core uut (Reg_output,address,number,jump,rst,clk);
initial begin
        clk = 1'b0;
        rst = 1'b0;
        jump = 1'b0;
end
always #5 clk = ~clk;
task load_program;
        input test_rst;
        input test_jump;
        input [31:0] test_address;
        input [31:0] test_number;
        input [31:0] exp_Reg_output;
        begin
                address = test_address;
                number = test_number;
                rst = test_rst;
                jump = test_jump;
                @(posedge clk);#1;
                test_num = test_num + 1;
                if(Reg_output !== exp_Reg_output) begin
                        $display("Test %d failed: expected Reg_output = %d, got Reg_output = %d", test_num, $signed(exp_Reg_output), $signed(Reg_output));
                        errors = errors + 1;
                end else begin
                        $display("Test %d passed: Reg_output = %d", test_num, $signed(Reg_output));
                end
        end                
endtask
initial begin
$dumpfile("dump.vcd");
$dumpvars(0,tb_riscv_core);
$timeformat(-9, 2, " ns", 10);
//$monitor("at time %t : | clk = %b | rst = %b | jump=%b |address = %d | number = %d | Reg_output = %d",$time,clk,rst,jump,address,number,Reg_output);
end
initial begin
        $display("----------------------------------------------------------------------------------------");
        $display("--------- start tasting ---------");
        $display("----------------------------------------------------------------------------------------");
        load_program(1'b1,1'b0,32'd0,32'b0,32'd0);
        load_program(1'b0,1'b0,32'd0,32'h00500093,32'h00000005);
        load_program(1'b0,1'b0,32'd1,32'h00A00113,32'h0000000A);
        load_program(1'b0,1'b0,32'd2,32'h002081B3,32'h0000000F);
        load_program(1'b0,1'b0,32'd3,32'hFFD18213,32'h0000000C);
        load_program(1'b0,1'b0,32'd4,32'h004202B3,32'h00000018);
        load_program(1'b0,1'b0,32'd5,32'hFFA00313,32'hFFFFFFFA);
        load_program(1'b0,1'b0,32'd6,32'h006283B3,32'h00000012);
        load_program(1'b0,1'b0,32'd7,32'h40638433,32'h00000018);
        load_program(1'b0,1'b0,32'd8,32'h0083F4B3,32'h00000010);
        load_program(1'b0,1'b0,32'd9,32'h0083E533,32'h0000001A);
        load_program(1'b0,1'b0,32'd10,32'h0083C5B3,32'h0000000A);
        load_program(1'b0,1'b0,32'd11,32'h0083B633,32'h00000001);
        load_program(1'b0,1'b0,32'd12,32'h0063A6B3,32'h0);
        load_program(1'b0,1'b0,32'd13,32'h00761733,32'h00040000);
        load_program(1'b0,1'b0,32'd14,32'h007757B3,32'h00000001);
        load_program(1'b0,1'b0,32'd15,32'h0103F813,32'h00000010);
        load_program(1'b0,1'b0,32'd16,32'h0103E893,32'h00000012);
        load_program(1'b0,1'b0,32'd17,32'h0103C913,32'h00000002);
        load_program(1'b0,1'b0,32'd18,32'h00239993,32'h00000048);
        load_program(1'b0,1'b0,32'd19,32'h0029DA13,32'h00000012);
        load_program(1'b0,1'b0,32'd20,32'h0023BA93,32'h0);
        load_program(1'b0,1'b0,32'd21,32'hFFE32B13,32'h00000001);
        load_program(1'b0,1'b1,32'd63,32'h0123F813,32'h00000012);
        load_program(1'b0,1'b0,32'd22,32'h0103F813,32'h00000010);
        load_program(1'b0,1'b1,32'd50,32'h0003F813,32'h0);
        load_program(1'b1,1'b0,32'b0,32'b0,32'b0);
        $display("----------------------------------------------------------------------------------------");
        if(errors == 0) begin
                $display("--------- All tests passed ---------");
        end else if (errors == 1) begin
                $display(" %d test failed ",errors);
        end else begin
                $display(" %d tests failed ",errors);
        end
        $display("----------------------------------------------------------------------------------------");
        $finish;
end
endmodule

dump.vcd
$date
	Sat Aug 15 23:51:16 2026
$end
$version
	Icarus Verilog
$end
$timescale
	1ps
$end
$scope module tb_riscv_core $end
$var wire 32 ! Reg_output [31:0] $end
$var reg 32 " address [31:0] $end
$var reg 1 # clk $end
$var reg 1 $ jump $end
$var reg 32 % number [31:0] $end
$var reg 1 & rst $end
$var integer 32 ' errors [31:0] $end
$var integer 32 ( test_num [31:0] $end
$scope module uut $end
$var wire 32 ) address [31:0] $end
$var wire 1 # clk $end
$var wire 1 $ jump $end
$var wire 32 * number [31:0] $end
$var wire 1 & rst $end
$var wire 5 + rs2 [4:0] $end
$var wire 5 , rs1 [4:0] $end
$var wire 32 - read_data2 [31:0] $end
$var wire 32 . read_data1 [31:0] $end
$var wire 5 / rd [4:0] $end
$var wire 32 0 pc_out [31:0] $end
$var wire 32 1 operand2 [31:0] $end
$var wire 7 2 opcode [6:0] $end
$var wire 32 3 instr [31:0] $end
$var wire 32 4 imm_out [31:0] $end
$var wire 7 5 funct7 [6:0] $end
$var wire 3 6 funct3 [2:0] $end
$var wire 1 7 flag $end
$var wire 32 8 fetch_address [31:0] $end
$var wire 32 9 alu_result [31:0] $end
$var wire 3 : alu_opcode [2:0] $end
$var wire 32 ; Reg_output [31:0] $end
$var wire 1 < RegWrite $end
$var wire 1 = ALUsrc $end
$scope module A1 $end
$var wire 1 # clk $end
$var wire 1 $ jump $end
$var wire 1 & rst $end
$var reg 32 > pc_out [31:0] $end
$upscope $end
$scope module A2 $end
$var wire 32 ? address [31:0] $end
$var wire 1 $ jump $end
$var wire 32 @ pc_out [31:0] $end
$var wire 32 A fetch_address [31:0] $end
$upscope $end
$scope module A3 $end
$var wire 32 B address [31:0] $end
$var wire 32 C instruction [31:0] $end
$var wire 32 D number [31:0] $end
$var wire 32 E pc_addr [31:0] $end
$upscope $end
$scope module A4 $end
$var wire 32 F instruction [31:0] $end
$var wire 32 G imm_out [31:0] $end
$upscope $end
$scope module A5 $end
$var wire 7 H opcode [6:0] $end
$var wire 1 < RegWrite $end
$var wire 1 = ALUSrc $end
$upscope $end
$scope module A6 $end
$var wire 1 < RegWrite $end
$var wire 1 # clk $end
$var wire 5 I rd [4:0] $end
$var wire 5 J rs1 [4:0] $end
$var wire 5 K rs2 [4:0] $end
$var wire 1 & rst $end
$var wire 32 L write_data [31:0] $end
$var wire 32 M read_data2 [31:0] $end
$var wire 32 N read_data1 [31:0] $end
$var reg 32 O Reg_output [31:0] $end
$var integer 32 P i [31:0] $end
$upscope $end
$scope module A7 $end
$var wire 1 = ALUsrc $end
$var wire 32 Q imm_out [31:0] $end
$var wire 32 R read_data2 [31:0] $end
$var wire 32 S operand2 [31:0] $end
$upscope $end
$scope module A8 $end
$var wire 3 T funct3 [2:0] $end
$var wire 7 U funct7 [6:0] $end
$var wire 7 V opcode [6:0] $end
$var wire 1 7 flag $end
$var reg 3 W alu_opcode [2:0] $end
$upscope $end
$scope module A9 $end
$var wire 3 X alu_opcode [2:0] $end
$var wire 1 7 flag $end
$var wire 32 Y operand1 [31:0] $end
$var wire 32 Z operand2 [31:0] $end
$var wire 32 [ result [31:0] $end
$var reg 32 \ res [31:0] $end
$upscope $end
$upscope $end
$scope task load_program $end
$var reg 32 ] exp_Reg_output [31:0] $end
$var reg 32 ^ test_address [31:0] $end
$var reg 1 _ test_jump $end
$var reg 32 ` test_number [31:0] $end
$var reg 1 a test_rst $end
$upscope $end
$upscope $end
$enddefinitions $end
$comment Show the parameter values. $end
$dumpall
$end
#0
$dumpvars
1a
b0 `
0_
b0 ^
b0 ]
bx \
bx [
bx Z
bx Y
bx X
bx W
bx V
bx U
bx T
bx S
bx R
bx Q
bx P
bx O
bx N
bx M
bx L
bx K
bx J
bx I
bx H
bx G
bx F
bx E
b0 D
bx C
b0 B
bx A
bx @
b0 ?
bx >
x=
x<
bx ;
bx :
bx 9
bx 8
x7
bx 6
bx 5
bx 4
bx 3
bx 2
bx 1
bx 0
bx /
bx .
bx -
bx ,
bx +
b0 *
b0 )
b0 (
b0 '
1&
b0 %
0$
0#
b0 "
bx !
$end
#5000
0<
b0 1
b0 S
b0 Z
b0 -
b0 M
b0 R
b0 .
b0 N
b0 Y
b0 9
b0 L
b0 [
b0 \
0=
b0 :
b0 W
b0 X
b0 4
b0 G
b0 Q
b0 5
b0 U
b0 +
b0 K
b0 ,
b0 J
07
b0 6
b0 T
b0 /
b0 I
b0 2
b0 H
b0 V
b0 3
b0 C
b0 F
b0 8
b0 A
b0 E
b0 0
b0 >
b0 @
b0 !
b0 ;
b0 O
b100000 P
1#
#6000
b101 9
b101 L
b101 [
b101 \
1<
b101 1
b101 S
b101 Z
1=
b101 4
b101 G
b101 Q
b101 +
b101 K
b1 /
b1 I
b10011 2
b10011 H
b10011 V
b10100000000000010010011 3
b10100000000000010010011 C
b10100000000000010010011 F
0&
b10100000000000010010011 %
b10100000000000010010011 *
b10100000000000010010011 D
b101 ]
b10100000000000010010011 `
0a
b1 (
#10000
0#
#15000
x<
bx 1
bx S
bx Z
bx -
bx M
bx R
bx .
bx N
bx Y
bx 9
bx L
bx [
bx \
x=
bx 4
bx G
bx Q
bx 5
bx U
bx +
bx K
bx ,
bx J
x7
bx 6
bx T
bx /
bx I
bx 2
bx H
bx V
bx 3
bx C
bx F
b100 8
b100 A
b100 E
b101 !
b101 ;
b101 O
b100 0
b100 >
b100 @
1#
#16000
1<
b1010 1
b1010 S
b1010 Z
b0 -
b0 M
b0 R
b0 .
b0 N
b0 Y
b1010 9
b1010 L
b1010 [
b1010 \
1=
b1010 4
b1010 G
b1010 Q
b0 5
b0 U
b1010 +
b1010 K
b0 ,
b0 J
07
b0 6
b0 T
b10 /
b10 I
b10011 2
b10011 H
b10011 V
b101000000000000100010011 3
b101000000000000100010011 C
b101000000000000100010011 F
b101000000000000100010011 %
b101000000000000100010011 *
b101000000000000100010011 D
b1 "
b1 )
b1 ?
b1 B
b1010 ]
b101000000000000100010011 `
b1 ^
b10 (
#20000
0#
#25000
x<
bx 1
bx S
bx Z
bx -
bx M
bx R
bx .
bx N
bx Y
bx 9
bx L
bx [
bx \
x=
bx 4
bx G
bx Q
bx 5
bx U
bx +
bx K
bx ,
bx J
x7
bx 6
bx T
bx /
bx I
bx 2
bx H
bx V
bx 3
bx C
bx F
b1000 8
b1000 A
b1000 E
b1000 0
b1000 >
b1000 @
b1010 !
b1010 ;
b1010 O
1#
#26000
1<
b1010 1
b1010 S
b1010 Z
b1010 -
b1010 M
b1010 R
b101 .
b101 N
b101 Y
b1111 9
b1111 L
b1111 [
b1111 \
0=
b10 4
b10 G
b10 Q
b0 5
b0 U
b10 +
b10 K
b1 ,
b1 J
07
b0 6
b0 T
b11 /
b11 I
b110011 2
b110011 H
b110011 V
b1000001000000110110011 3
b1000001000000110110011 C
b1000001000000110110011 F
b1000001000000110110011 %
b1000001000000110110011 *
b1000001000000110110011 D
b10 "
b10 )
b10 ?
b10 B
b1111 ]
b1000001000000110110011 `
b10 ^
b11 (
#30000
0#
#35000
x<
bx 1
bx S
bx Z
bx -
bx M
bx R
bx .
bx N
bx Y
bx 9
bx L
bx [
bx \
x=
bx 4
bx G
bx Q
bx 5
bx U
bx +
bx K
bx ,
bx J
x7
bx 6
bx T
bx /
bx I
bx 2
bx H
bx V
bx 3
bx C
bx F
b1100 8
b1100 A
b1100 E
b1111 !
b1111 ;
b1111 O
b1100 0
b1100 >
b1100 @
1#
#36000
1<
b11111111111111111111111111111101 1
b11111111111111111111111111111101 S
b11111111111111111111111111111101 Z
b0 -
b0 M
b0 R
b1111 .
b1111 N
b1111 Y
b1100 9
b1100 L
b1100 [
b1100 \
1=
b11111111111111111111111111111101 4
b11111111111111111111111111111101 G
b11111111111111111111111111111101 Q
b1111111 5
b1111111 U
b11101 +
b11101 K
b11 ,
b11 J
07
b0 6
b0 T
b100 /
b100 I
b10011 2
b10011 H
b10011 V
b11111111110100011000001000010011 3
b11111111110100011000001000010011 C
b11111111110100011000001000010011 F
b11111111110100011000001000010011 %
b11111111110100011000001000010011 *
b11111111110100011000001000010011 D
b11 "
b11 )
b11 ?
b11 B
b1100 ]
b11111111110100011000001000010011 `
b11 ^
b100 (
#40000
0#
#45000
x<
bx 1
bx S
bx Z
bx -
bx M
bx R
bx .
bx N
bx Y
bx 9
bx L
bx [
bx \
x=
bx 4
bx G
bx Q
bx 5
bx U
bx +
bx K
bx ,
bx J
x7
bx 6
bx T
bx /
bx I
bx 2
bx H
bx V
bx 3
bx C
bx F
b10000 8
b10000 A
b10000 E
b10000 0
b10000 >
b10000 @
b1100 !
b1100 ;
b1100 O
1#
#46000
1<
b1100 1
b1100 S
b1100 Z
b1100 -
b1100 M
b1100 R
b1100 .
b1100 N
b1100 Y
b11000 9
b11000 L
b11000 [
b11000 \
0=
b100 4
b100 G
b100 Q
b0 5
b0 U
b100 +
b100 K
b100 ,
b100 J
07
b0 6
b0 T
b101 /
b101 I
b110011 2
b110011 H
b110011 V
b10000100000001010110011 3
b10000100000001010110011 C
b10000100000001010110011 F
b10000100000001010110011 %
b10000100000001010110011 *
b10000100000001010110011 D
b100 "
b100 )
b100 ?
b100 B
b11000 ]
b10000100000001010110011 `
b100 ^
b101 (
#50000
0#
#55000
x<
bx 1
bx S
bx Z
bx -
bx M
bx R
bx .
bx N
bx Y
bx 9
bx L
bx [
bx \
x=
bx 4
bx G
bx Q
bx 5
bx U
bx +
bx K
bx ,
bx J
x7
bx 6
bx T
bx /
bx I
bx 2
bx H
bx V
bx 3
bx C
bx F
b10100 8
b10100 A
b10100 E
b11000 !
b11000 ;
b11000 O
b10100 0
b10100 >
b10100 @
1#
#56000
1<
b11111111111111111111111111111010 1
b11111111111111111111111111111010 S
b11111111111111111111111111111010 Z
b0 -
b0 M
b0 R
b0 .
b0 N
b0 Y
b11111111111111111111111111111010 9
b11111111111111111111111111111010 L
b11111111111111111111111111111010 [
b11111111111111111111111111111010 \
1=
b11111111111111111111111111111010 4
b11111111111111111111111111111010 G
b11111111111111111111111111111010 Q
b1111111 5
b1111111 U
b11010 +
b11010 K
b0 ,
b0 J
07
b0 6
b0 T
b110 /
b110 I
b10011 2
b10011 H
b10011 V
b11111111101000000000001100010011 3
b11111111101000000000001100010011 C
b11111111101000000000001100010011 F
b11111111101000000000001100010011 %
b11111111101000000000001100010011 *
b11111111101000000000001100010011 D
b101 "
b101 )
b101 ?
b101 B
b11111111111111111111111111111010 ]
b11111111101000000000001100010011 `
b101 ^
b110 (
#60000
0#
#65000
x<
bx 1
bx S
bx Z
bx -
bx M
bx R
bx .
bx N
bx Y
bx 9
bx L
bx [
bx \
x=
bx 4
bx G
bx Q
bx 5
bx U
bx +
bx K
bx ,
bx J
x7
bx 6
bx T
bx /
bx I
bx 2
bx H
bx V
bx 3
bx C
bx F
b11000 8
b11000 A
b11000 E
b11000 0
b11000 >
b11000 @
b11111111111111111111111111111010 !
b11111111111111111111111111111010 ;
b11111111111111111111111111111010 O
1#
#66000
1<
b11111111111111111111111111111010 1
b11111111111111111111111111111010 S
b11111111111111111111111111111010 Z
b11111111111111111111111111111010 -
b11111111111111111111111111111010 M
b11111111111111111111111111111010 R
b11000 .
b11000 N
b11000 Y
b10010 9
b10010 L
b10010 [
b10010 \
0=
b110 4
b110 G
b110 Q
b0 5
b0 U
b110 +
b110 K
b101 ,
b101 J
07
b0 6
b0 T
b111 /
b111 I
b110011 2
b110011 H
b110011 V
b11000101000001110110011 3
b11000101000001110110011 C
b11000101000001110110011 F
b11000101000001110110011 %
b11000101000001110110011 *
b11000101000001110110011 D
b110 "
b110 )
b110 ?
b110 B
b10010 ]
b11000101000001110110011 `
b110 ^
b111 (
#70000
0#
#75000
x<
bx 1
bx S
bx Z
bx -
bx M
bx R
bx .
bx N
bx Y
bx 9
bx L
bx [
bx \
x=
bx 4
bx G
bx Q
bx 5
bx U
bx +
bx K
bx ,
bx J
x7
bx 6
bx T
bx /
bx I
bx 2
bx H
bx V
bx 3
bx C
bx F
b11100 8
b11100 A
b11100 E
b10010 !
b10010 ;
b10010 O
b11100 0
b11100 >
b11100 @
1#
#76000
1<
b11111111111111111111111111111010 1
b11111111111111111111111111111010 S
b11111111111111111111111111111010 Z
b11111111111111111111111111111010 -
b11111111111111111111111111111010 M
b11111111111111111111111111111010 R
b10010 .
b10010 N
b10010 Y
b11000 9
b11000 L
b11000 [
b11000 \
0=
b1 :
b1 W
b1 X
b10000000110 4
b10000000110 G
b10000000110 Q
b100000 5
b100000 U
b110 +
b110 K
b111 ,
b111 J
07
b0 6
b0 T
b1000 /
b1000 I
b110011 2
b110011 H
b110011 V
b1000000011000111000010000110011 3
b1000000011000111000010000110011 C
b1000000011000111000010000110011 F
b1000000011000111000010000110011 %
b1000000011000111000010000110011 *
b1000000011000111000010000110011 D
b111 "
b111 )
b111 ?
b111 B
b11000 ]
b1000000011000111000010000110011 `
b111 ^
b1000 (
#80000
0#
#85000
x<
bx 1
bx S
bx Z
bx -
bx M
bx R
bx .
bx N
bx Y
bx 9
bx L
bx [
bx \
x=
b0 :
b0 W
b0 X
bx 4
bx G
bx Q
bx 5
bx U
bx +
bx K
bx ,
bx J
x7
bx 6
bx T
bx /
bx I
bx 2
bx H
bx V
bx 3
bx C
bx F
b100000 8
b100000 A
b100000 E
b100000 0
b100000 >
b100000 @
b11000 !
b11000 ;
b11000 O
1#
#86000
1<
b11000 1
b11000 S
b11000 Z
b11000 -
b11000 M
b11000 R
b10010 .
b10010 N
b10010 Y
b10000 9
b10000 L
b10000 [
b10000 \
0=
b10 :
b10 W
b10 X
b1000 4
b1000 G
b1000 Q
b0 5
b0 U
b1000 +
b1000 K
b111 ,
b111 J
07
b111 6
b111 T
b1001 /
b1001 I
b110011 2
b110011 H
b110011 V
b100000111111010010110011 3
b100000111111010010110011 C
b100000111111010010110011 F
b100000111111010010110011 %
b100000111111010010110011 *
b100000111111010010110011 D
b1000 "
b1000 )
b1000 ?
b1000 B
b10000 ]
b100000111111010010110011 `
b1000 ^
b1001 (
#90000
0#
#95000
x<
bx 1
bx S
bx Z
bx -
bx M
bx R
bx .
bx N
bx Y
bx 9
bx L
bx [
bx \
x=
b0 :
b0 W
b0 X
bx 4
bx G
bx Q
bx 5
bx U
bx +
bx K
bx ,
bx J
x7
bx 6
bx T
bx /
bx I
bx 2
bx H
bx V
bx 3
bx C
bx F
b100100 8
b100100 A
b100100 E
b10000 !
b10000 ;
b10000 O
b100100 0
b100100 >
b100100 @
1#
#96000
1<
b11000 1
b11000 S
b11000 Z
b11000 -
b11000 M
b11000 R
b10010 .
b10010 N
b10010 Y
b11010 9
b11010 L
b11010 [
b11010 \
0=
b11 :
b11 W
b11 X
b1000 4
b1000 G
b1000 Q
b0 5
b0 U
b1000 +
b1000 K
b111 ,
b111 J
07
b110 6
b110 T
b1010 /
b1010 I
b110011 2
b110011 H
b110011 V
b100000111110010100110011 3
b100000111110010100110011 C
b100000111110010100110011 F
b100000111110010100110011 %
b100000111110010100110011 *
b100000111110010100110011 D
b1001 "
b1001 )
b1001 ?
b1001 B
b11010 ]
b100000111110010100110011 `
b1001 ^
b1010 (
#100000
0#
#105000
x<
bx 1
bx S
bx Z
bx -
bx M
bx R
bx .
bx N
bx Y
bx 9
bx L
bx [
bx \
x=
b0 :
b0 W
b0 X
bx 4
bx G
bx Q
bx 5
bx U
bx +
bx K
bx ,
bx J
x7
bx 6
bx T
bx /
bx I
bx 2
bx H
bx V
bx 3
bx C
bx F
b101000 8
b101000 A
b101000 E
b101000 0
b101000 >
b101000 @
b11010 !
b11010 ;
b11010 O
1#
#106000
1<
b11000 1
b11000 S
b11000 Z
b11000 -
b11000 M
b11000 R
b10010 .
b10010 N
b10010 Y
b1010 9
b1010 L
b1010 [
b1010 \
0=
b100 :
b100 W
b100 X
b1000 4
b1000 G
b1000 Q
b0 5
b0 U
b1000 +
b1000 K
b111 ,
b111 J
07
b100 6
b100 T
b1011 /
b1011 I
b110011 2
b110011 H
b110011 V
b100000111100010110110011 3
b100000111100010110110011 C
b100000111100010110110011 F
b100000111100010110110011 %
b100000111100010110110011 *
b100000111100010110110011 D
b1010 "
b1010 )
b1010 ?
b1010 B
b1010 ]
b100000111100010110110011 `
b1010 ^
b1011 (
#110000
0#
#115000
x<
bx 1
bx S
bx Z
bx -
bx M
bx R
bx .
bx N
bx Y
bx 9
bx L
bx [
bx \
x=
b0 :
b0 W
b0 X
bx 4
bx G
bx Q
bx 5
bx U
bx +
bx K
bx ,
bx J
x7
bx 6
bx T
bx /
bx I
bx 2
bx H
bx V
bx 3
bx C
bx F
b101100 8
b101100 A
b101100 E
b1010 !
b1010 ;
b1010 O
b101100 0
b101100 >
b101100 @
1#
#116000
1<
b11000 1
b11000 S
b11000 Z
b11000 -
b11000 M
b11000 R
b10010 .
b10010 N
b10010 Y
b1 9
b1 L
b1 [
b1 \
0=
b101 :
b101 W
b101 X
b1000 4
b1000 G
b1000 Q
b0 5
b0 U
b1000 +
b1000 K
b111 ,
b111 J
07
b11 6
b11 T
b1100 /
b1100 I
b110011 2
b110011 H
b110011 V
b100000111011011000110011 3
b100000111011011000110011 C
b100000111011011000110011 F
b100000111011011000110011 %
b100000111011011000110011 *
b100000111011011000110011 D
b1011 "
b1011 )
b1011 ?
b1011 B
b1 ]
b100000111011011000110011 `
b1011 ^
b1100 (
#120000
0#
#125000
x<
bx 1
bx S
bx Z
bx -
bx M
bx R
bx .
bx N
bx Y
bx 9
bx L
bx [
bx \
x=
b0 :
b0 W
b0 X
bx 4
bx G
bx Q
bx 5
bx U
bx +
bx K
bx ,
bx J
x7
bx 6
bx T
bx /
bx I
bx 2
bx H
bx V
bx 3
bx C
bx F
b110000 8
b110000 A
b110000 E
b110000 0
b110000 >
b110000 @
b1 !
b1 ;
b1 O
1#
#126000
1<
b11111111111111111111111111111010 1
b11111111111111111111111111111010 S
b11111111111111111111111111111010 Z
b11111111111111111111111111111010 -
b11111111111111111111111111111010 M
b11111111111111111111111111111010 R
b10010 .
b10010 N
b10010 Y
b0 9
b0 L
b0 [
b0 \
0=
b101 :
b101 W
b101 X
b110 4
b110 G
b110 Q
b0 5
b0 U
b110 +
b110 K
b111 ,
b111 J
17
b10 6
b10 T
b1101 /
b1101 I
b110011 2
b110011 H
b110011 V
b11000111010011010110011 3
b11000111010011010110011 C
b11000111010011010110011 F
b11000111010011010110011 %
b11000111010011010110011 *
b11000111010011010110011 D
b1100 "
b1100 )
b1100 ?
b1100 B
b0 ]
b11000111010011010110011 `
b1100 ^
b1101 (
#130000
0#
#135000
x<
bx 1
bx S
bx Z
bx -
bx M
bx R
bx .
bx N
bx Y
bx 9
bx L
bx [
bx \
x=
b0 :
b0 W
b0 X
bx 4
bx G
bx Q
bx 5
bx U
bx +
bx K
bx ,
bx J
x7
bx 6
bx T
bx /
bx I
bx 2
bx H
bx V
bx 3
bx C
bx F
b110100 8
b110100 A
b110100 E
b0 !
b0 ;
b0 O
b110100 0
b110100 >
b110100 @
1#
#136000
1<
b10010 1
b10010 S
b10010 Z
b10010 -
b10010 M
b10010 R
b1 .
b1 N
b1 Y
b1000000000000000000 9
b1000000000000000000 L
b1000000000000000000 [
b1000000000000000000 \
0=
b110 :
b110 W
b110 X
b111 4
b111 G
b111 Q
b0 5
b0 U
b111 +
b111 K
b1100 ,
b1100 J
07
b1 6
b1 T
b1110 /
b1110 I
b110011 2
b110011 H
b110011 V
b11101100001011100110011 3
b11101100001011100110011 C
b11101100001011100110011 F
b11101100001011100110011 %
b11101100001011100110011 *
b11101100001011100110011 D
b1101 "
b1101 )
b1101 ?
b1101 B
b1000000000000000000 ]
b11101100001011100110011 `
b1101 ^
b1110 (
#140000
0#
#145000
x<
bx 1
bx S
bx Z
bx -
bx M
bx R
bx .
bx N
bx Y
bx 9
bx L
bx [
bx \
x=
b0 :
b0 W
b0 X
bx 4
bx G
bx Q
bx 5
bx U
bx +
bx K
bx ,
bx J
x7
bx 6
bx T
bx /
bx I
bx 2
bx H
bx V
bx 3
bx C
bx F
b111000 8
b111000 A
b111000 E
b111000 0
b111000 >
b111000 @
b1000000000000000000 !
b1000000000000000000 ;
b1000000000000000000 O
1#
#146000
1<
b10010 1
b10010 S
b10010 Z
b10010 -
b10010 M
b10010 R
b1000000000000000000 .
b1000000000000000000 N
b1000000000000000000 Y
b1 9
b1 L
b1 [
b1 \
0=
b111 :
b111 W
b111 X
b111 4
b111 G
b111 Q
b0 5
b0 U
b111 +
b111 K
b1110 ,
b1110 J
07
b101 6
b101 T
b1111 /
b1111 I
b110011 2
b110011 H
b110011 V
b11101110101011110110011 3
b11101110101011110110011 C
b11101110101011110110011 F
b11101110101011110110011 %
b11101110101011110110011 *
b11101110101011110110011 D
b1110 "
b1110 )
b1110 ?
b1110 B
b1 ]
b11101110101011110110011 `
b1110 ^
b1111 (
#150000
0#
