ALU_RISC-V.v
module ALU_RISCV(result,operand1,operand2,alu_opcode);
input [31:0] operand1,operand2;
input [2:0] alu_opcode;
output [31:0] result;
reg [31:0] res;
always @(*) begin
        res = 32'b0;
        case(alu_opcode)
                3'b000: res = operand1 + operand2; // ADD
                3'b001: res = operand1 - operand2; // SUB
                3'b010: res = operand1 & operand2; // AND
                3'b011: res = operand1 | operand2; // OR
                3'b100: res = operand1 ^ operand2; // XOR
                3'b101: res = (operand1 < operand2) ? 32'b1 : 32'b0; // SLT
                3'b110: res = operand1 << operand2[4:0]; // SLL
                3'b111: res = operand1 >> operand2[4:0]; // SRL
                default : res = 32'b0;
        endcase
end
assign result = res;
endmodule

alu_control.v
module alu_control(alu_opcode,funct3,funct7,opcode);
input [2:0] funct3;
input [6:0] funct7, opcode;
output reg [2:0] alu_opcode;
always @ (*) begin
        case(opcode)
                7'b0110011 : begin
                        case(funct3)
                                3'b000 : alu_opcode = (funct7 == 7'b0100000) ? 3'b001 : 3'b000;
                                default : alu_opcode = 3'b0;
                        endcase
                end
                7'b0010011 : begin
                        alu_opcode = 3'b000;
                end
                default : alu_opcode = 3'b000;
        endcase
end
endmodule

alu_src_mux.v
module alu_src_mux(operand2,imm_out,read_data2,ALUsrc);
input ALUsrc;
input [31:0] imm_out ,read_data2;
output [31:0] operand2;
assign operand2 = ALUsrc ? imm_out : read_data2 ;
endmodule

register_file.v
module register_file(read_data1,read_data2,write_data,rd,rs1,rs2,RegWrite,rst,clk);
input clk,rst,RegWrite;
input [4:0] rd,rs1,rs2;
output [31:0] read_data1,read_data2;
input [31:0] write_data;
reg [31:0] Reg [0:31];
integer i;
always @ (posedge clk) begin
        if (rst) begin 
                for(i = 0; i < 32 ; i = i + 1) begin
                        Reg[i] <= 32'b0;
                end
        end else begin
                if (RegWrite) begin
                        Reg[rd] <= write_data;
                end else begin
                        Reg[rd] <= Reg[rd];
                end
        end
end
assign read_data1 = (rs1 == 5'b0) ? 32'b0 : Reg[rs1];
assign read_data2 = (rs2 == 5'b0) ? 32'b0 : Reg[rs2];
endmodule

control_unit.v
module control_unit(RegWrite,ALUSrc,opcode);
input [6:0] opcode;
output RegWrite,ALUSrc;
assign RegWrite = (opcode == 7'b0110011 || opcode == 7'b0010011) ? 1'b1 : 1'b0;
assign ALUSrc = (opcode == 7'b0010011) ? 1'b1 : 1'b0;
endmodule

imm_gen.v
module imm_gen(imm_out,instruction);
input [31:0] instruction;
output [31:0] imm_out;
assign imm_out = {{20{instruction[31]}},instruction[31:20]};
endmodule

instr_mem.v
module instr_mem(instruction,pc_addr);
input [31:0] pc_addr;
output [31:0] instruction;
reg [31:0] mem [0:63];
assign instruction = mem[pc_addr[31:2]];
endmodule

pc_reg.v
module pc_reg(pc_out,rst,clk);
input rst,clk;
output reg [31:0] pc_out;
always @ (posedge clk) begin
        if (rst) begin
                pc_out <= 32'b0;
        end else begin
                pc_out <= pc_out + 32'b00000000000000000000000000000100;
        end
end
endmodule

Riscv_core.v
module riscv_core(pc_out,rst,clk);
input rst,clk;
output [31:0] pc_out;
wire [4:0] rd,rs1,rs2;
wire RegWrite,ALUsrc;
wire [6:0] opcode,funct7;
wire [2:0] alu_opcode,funct3;
wire [31:0] read_data1,read_data2,w1,imm_out,operand2,alu_result,instr;
pc_reg A1 (w1,rst,clk);
instr_mem A2 (instr,w1);
assign opcode = instr[6:0];
assign rd = instr[11:7];
assign funct3 = instr[14:12];
assign rs1 = instr[19:15];
assign rs2 = instr[24:20];
assign funct7 = instr[31:25];
assign pc_out = w1;
imm_gen A3 (imm_out,instr);
control_unit A4 (RegWrite,ALUsrc,opcode);
register_file A5 (read_data1,read_data2,alu_result,rd,rs1,rs2,RegWrite,rst,clk);
alu_src_mux A6 (operand2,imm_out,read_data2,ALUsrc);
alu_control A7 (alu_opcode,funct3,funct7,opcode);
ALU_RISCV A8 (alu_result,read_data1,operand2,alu_opcode);
endmodule

tb_riscv_core.v
`timescale 1ns / 1ps
module tb_riscv_core;
reg rst,clk;
wire [31:0] pc_out;
riscv_core uut (pc_out,rst,clk);
initial begin
        clk = 1'b0;
        rst = 1'b0;
end
always #5 clk = ~clk;
initial begin
$dumpfile("dump.vcd");
$dumpvars(0,tb_riscv_core);
$monitor("at time %t : clk = %b rst = %b pc_out=%b",$time,clk,rst,pc_out);
                rst = 1'b1; #10;
                uut.A2.mem[0] = 32'h00500093;
                uut.A2.mem[1] = 32'h00A00113;
                uut.A2.mem[2] = 32'h002081B3;
                uut.A2.mem[3] = 32'hFFD18213;
                uut.A2.mem[4] = 32'h004202B3;
                uut.A2.mem[5] = 32'hFFA00313;
                uut.A2.mem[6] = 32'h006283B3;
                uut.A2.mem[7] = 32'h40638433;
                rst = 1'b0;#10;
                #70;
                $display("---- Final Register Values ----");
                $display("x1 = %0d (expected 5)",  uut.A5.Reg[1]);
                $display("x2 = %0d (expected 10)", uut.A5.Reg[2]);
                $display("x3 = %0d (expected 15)", uut.A5.Reg[3]);
                $display("x4 = %0d (expected 12)", uut.A5.Reg[4]);
                $display("x5 = %0d (expected 24)", uut.A5.Reg[5]);
                $display("x6 = %0d (expected -6)", $signed(uut.A5.Reg[6]));
                $display("x7 = %0d (expected 18)", uut.A5.Reg[7]);
                $display("x8 = %0d (expected 24)", uut.A5.Reg[8]);
        $finish;
end
endmodule

dump.vcd
$date
	Wed Jul 08 13:51:20 2026
$end
$version
	Icarus Verilog
$end
$timescale
	1ps
$end
$scope module tb_riscv_core $end
$var wire 32 ! pc_out [31:0] $end
$var reg 1 " clk $end
$var reg 1 # rst $end
$scope module uut $end
$var wire 1 " clk $end
$var wire 32 $ pc_out [31:0] $end
$var wire 1 # rst $end
$var wire 32 % w1 [31:0] $end
$var wire 5 & rs2 [4:0] $end
$var wire 5 ' rs1 [4:0] $end
$var wire 32 ( read_data2 [31:0] $end
$var wire 32 ) read_data1 [31:0] $end
$var wire 5 * rd [4:0] $end
$var wire 32 + operand2 [31:0] $end
$var wire 7 , opcode [6:0] $end
$var wire 32 - instr [31:0] $end
$var wire 32 . imm_out [31:0] $end
$var wire 7 / funct7 [6:0] $end
$var wire 3 0 funct3 [2:0] $end
$var wire 32 1 alu_result [31:0] $end
$var wire 3 2 alu_opcode [2:0] $end
$var wire 1 3 RegWrite $end
$var wire 1 4 ALUsrc $end
$scope module A1 $end
$var wire 1 " clk $end
$var wire 1 # rst $end
$var reg 32 5 pc_out [31:0] $end
$upscope $end
$scope module A2 $end
$var wire 32 6 instruction [31:0] $end
$var wire 32 7 pc_addr [31:0] $end
$upscope $end
$scope module A3 $end
$var wire 32 8 instruction [31:0] $end
$var wire 32 9 imm_out [31:0] $end
$upscope $end
$scope module A4 $end
$var wire 7 : opcode [6:0] $end
$var wire 1 3 RegWrite $end
$var wire 1 4 ALUSrc $end
$upscope $end
$scope module A5 $end
$var wire 1 3 RegWrite $end
$var wire 1 " clk $end
$var wire 5 ; rd [4:0] $end
$var wire 5 < rs1 [4:0] $end
$var wire 5 = rs2 [4:0] $end
$var wire 1 # rst $end
$var wire 32 > write_data [31:0] $end
$var wire 32 ? read_data2 [31:0] $end
$var wire 32 @ read_data1 [31:0] $end
$var integer 32 A i [31:0] $end
$upscope $end
$scope module A6 $end
$var wire 1 4 ALUsrc $end
$var wire 32 B imm_out [31:0] $end
$var wire 32 C read_data2 [31:0] $end
$var wire 32 D operand2 [31:0] $end
$upscope $end
$scope module A7 $end
$var wire 3 E funct3 [2:0] $end
$var wire 7 F funct7 [6:0] $end
$var wire 7 G opcode [6:0] $end
$var reg 3 H alu_opcode [2:0] $end
$upscope $end
$scope module A8 $end
$var wire 3 I alu_opcode [2:0] $end
$var wire 32 J operand1 [31:0] $end
$var wire 32 K operand2 [31:0] $end
$var wire 32 L result [31:0] $end
$var reg 32 M res [31:0] $end
$upscope $end
$upscope $end
$upscope $end
$enddefinitions $end
$comment Show the parameter values. $end
$dumpall
$end
#0
$dumpvars
bx M
bx L
bx K
bx J
bx I
bx H
bx G
bx F
bx E
bx D
bx C
bx B
bx A
bx @
bx ?
bx >
bx =
bx <
bx ;
bx :
bx 9
bx 8
bx 7
bx 6
bx 5
x4
x3
bx 2
bx 1
bx 0
bx /
bx .
bx -
bx ,
bx +
bx *
bx )
bx (
bx '
bx &
bx %
bx $
1#
0"
bx !
$end
#5000
b0 !
b0 $
b0 %
b0 5
b0 7
b100000 A
1"
#10000
13
b101 1
b101 >
b101 L
b101 M
b101 +
b101 D
b101 K
b0 (
b0 ?
b0 C
b0 )
b0 @
b0 J
14
b0 2
b0 H
b0 I
b101 .
b101 9
b101 B
b0 /
b0 F
b101 &
b101 =
b0 '
b0 <
b0 0
b0 E
b1 *
b1 ;
b10011 ,
b10011 :
b10011 G
0"
0#
b10100000000000010010011 -
b10100000000000010010011 6
b10100000000000010010011 8
#15000
b1010 1
b1010 >
b1010 L
b1010 M
b1010 +
b1010 D
b1010 K
b1010 .
b1010 9
b1010 B
b1010 &
b1010 =
b10 *
b10 ;
b101000000000000100010011 -
b101000000000000100010011 6
b101000000000000100010011 8
b100 !
b100 $
b100 %
b100 5
b100 7
1"
#20000
0"
#25000
b1111 1
b1111 >
b1111 L
b1111 M
b1010 (
b1010 ?
b1010 C
b101 )
b101 @
b101 J
04
b10 .
b10 9
b10 B
b10 &
b10 =
b1 '
b1 <
b11 *
b11 ;
b110011 ,
b110011 :
b110011 G
b1000001000000110110011 -
b1000001000000110110011 6
b1000001000000110110011 8
b1000 !
b1000 $
b1000 %
b1000 5
b1000 7
1"
#30000
0"
#35000
b1100 1
b1100 >
b1100 L
b1100 M
b11111111111111111111111111111101 +
b11111111111111111111111111111101 D
b11111111111111111111111111111101 K
b0 (
b0 ?
b0 C
b1111 )
b1111 @
b1111 J
14
b11111111111111111111111111111101 .
b11111111111111111111111111111101 9
b11111111111111111111111111111101 B
b1111111 /
b1111111 F
b11101 &
b11101 =
b11 '
b11 <
b100 *
b100 ;
b10011 ,
b10011 :
b10011 G
b11111111110100011000001000010011 -
b11111111110100011000001000010011 6
b11111111110100011000001000010011 8
b1100 !
b1100 $
b1100 %
b1100 5
b1100 7
1"
#40000
0"
#45000
b11000 1
b11000 >
b11000 L
b11000 M
b1100 +
b1100 D
b1100 K
b1100 (
b1100 ?
b1100 C
b1100 )
b1100 @
b1100 J
04
b100 .
b100 9
b100 B
b0 /
b0 F
b100 &
b100 =
b100 '
b100 <
b101 *
b101 ;
b110011 ,
b110011 :
b110011 G
b10000100000001010110011 -
b10000100000001010110011 6
b10000100000001010110011 8
b10000 !
b10000 $
b10000 %
b10000 5
b10000 7
1"
#50000
0"
#55000
b11111111111111111111111111111010 1
b11111111111111111111111111111010 >
b11111111111111111111111111111010 L
b11111111111111111111111111111010 M
b11111111111111111111111111111010 +
b11111111111111111111111111111010 D
b11111111111111111111111111111010 K
b0 (
b0 ?
b0 C
b0 )
b0 @
b0 J
14
b11111111111111111111111111111010 .
b11111111111111111111111111111010 9
b11111111111111111111111111111010 B
b1111111 /
b1111111 F
b11010 &
b11010 =
b0 '
b0 <
b110 *
b110 ;
b10011 ,
b10011 :
b10011 G
b11111111101000000000001100010011 -
b11111111101000000000001100010011 6
b11111111101000000000001100010011 8
b10100 !
b10100 $
b10100 %
b10100 5
b10100 7
1"
#60000
0"
#65000
b10010 1
b10010 >
b10010 L
b10010 M
b11111111111111111111111111111010 (
b11111111111111111111111111111010 ?
b11111111111111111111111111111010 C
b11000 )
b11000 @
b11000 J
04
b110 .
b110 9
b110 B
b0 /
b0 F
b110 &
b110 =
b101 '
b101 <
b111 *
b111 ;
b110011 ,
b110011 :
b110011 G
b11000101000001110110011 -
b11000101000001110110011 6
b11000101000001110110011 8
b11000 !
b11000 $
b11000 %
b11000 5
b11000 7
1"
#70000
0"
#75000
b11000 1
b11000 >
b11000 L
b11000 M
b1 2
b1 H
b1 I
b10010 )
b10010 @
b10010 J
b10000000110 .
b10000000110 9
b10000000110 B
b100000 /
b100000 F
b111 '
b111 <
b1000 *
b1000 ;
b1000000011000111000010000110011 -
b1000000011000111000010000110011 6
b1000000011000111000010000110011 8
b11100 !
b11100 $
b11100 %
b11100 5
b11100 7
1"
#80000
0"
#85000
x3
bx +
bx D
bx K
bx 1
bx >
bx L
bx M
bx (
bx ?
bx C
bx )
bx @
bx J
x4
b0 2
b0 H
b0 I
bx .
bx 9
bx B
bx /
bx F
bx &
bx =
bx '
bx <
bx 0
bx E
bx *
bx ;
bx ,
bx :
bx G
bx -
bx 6
bx 8
b100000 !
b100000 $
b100000 %
b100000 5
b100000 7
1"
